downloader_cli/__init__.py
downloader_cli/__version__.py
downloader_cli/color.py
downloader_cli/download.py
downloader_cli/main.py
downloader_cli-0.3.4.dist-info/LICENSE
downloader_cli-0.3.4.dist-info/METADATA
downloader_cli-0.3.4.dist-info/WHEEL
downloader_cli-0.3.4.dist-info/entry_points.txt
downloader_cli-0.3.4.dist-info/top_level.txt
downloader_cli-0.3.4.dist-info/RECORD
