Metadata-Version: 2.1
Name: downloader_cli
Version: 0.3.4
Summary: A simple downloader written in Python with an awesome progressbar.
Home-page: https://github.com/deepjyoti30/downloader-cli
Author: Deepjyoti Barman
Author-email: deep.barman30@gmail.com
Classifier: Programming Language :: Python :: 3
Classifier: License :: OSI Approved :: MIT License
Classifier: Operating System :: OS Independent
License-File: LICENSE
Requires-Dist: urllib3>=1.25.6
